LICENSE
README.md
setup.py
opentracing_kafka/__init__.py
opentracing_kafka/tracing_kafka_consumer.py
opentracing_kafka/tracing_kafka_producer.py
opentracing_kafka/utils.py
opentracing_python_kafka_client.egg-info/PKG-INFO
opentracing_python_kafka_client.egg-info/SOURCES.txt
opentracing_python_kafka_client.egg-info/dependency_links.txt
opentracing_python_kafka_client.egg-info/not-zip-safe
opentracing_python_kafka_client.egg-info/requires.txt
opentracing_python_kafka_client.egg-info/top_level.txt
test/test_tracing_kafka_consumerr.py
test/test_tracing_kafka_producer.py