Metadata-Version: 1.0
Name: opentracing-python-kafka-client
Version: 1.2
Summary: OpenTracing Instrumentation for Confluent-Kafka-Python library
Home-page: https://github.com/shakti-garg/opentracing-python-kafka-client.git
Author: Shakti Garg
Author-email: shakti.garg@gmail.com
License: Apache License Version 2.0
Platform: UNKNOWN
